{
  "date": "2026-05-09",
  "dateLabel": "2026-5-9",
  "title": "다주택자 세금 유예 끝, 시장 요동 시작",
  "news": [
    "다주택자 양도세 중과 유예가 10일부터 종료되면서 매매와 전세 시장이 동시에 요동치고 있다.",
    "등록임대 양도세 특례도 손볼 예정으로, 전세 매물 감소 우려가 커지고 있다.",
    "서울 강남과 용산을 중심으로 매매가 오르면서 전세가격도 함께 상승 중이다."
  ],
  "intent": "정부는 공급을 늘려서 집값을 잡으려는 정책을 펴고 있다. 다주택자에게 세금을 많이 걷어서 투기를 줄이고, 실제로 살 사람 중심의 시장으로 만들려는 거다. 등록임대 특례도 손보는 이유는 일부 부자들이 세금 혜택으로 집을 묶어두는 걸 막으려는 것이다.",
  "market": "세금 유예가 끝나자 다주택자들이 빌린 돈을 갚고 집을 내놓으면서 매매 시장에 물건이 나올 것 같다. 하지만 이들이 세를 놓던 집까지 줄어들면서 전세 시장은 더 비싸질 수 있다. 결국 매매는 조금 풀릴 것 같은데 전세는 더 뜨거워질 것 같은 상황이다.",
  "demand": {
    "buy": "지금은 다주택자들이 집을 팔려고 나올 시기라 물건이 좀 많아질 수 있지만, 여전히 공급 자체는 부족해 보인다.",
    "lease": "전세를 구하려면 더 비싼 값을 제시하거나, 월세로 바꿀 준비를 해야 할 시점이다.",
    "rent": "전세가 비싸지면서 월세 수요도 늘어날 텐데, 월세 가격도 함께 오를 가능성이 높다."
  }
}