[
  {
    "date": "2026-05-02",
    "title": "강남 규제에 중하위 지역 집값 상승, 전세난 심화"
  },
  {
    "date": "2026-04-28",
    "title": "오르긴 오르는데 속도가 꺾였다, 강남은 2개월째 하락"
  },
  {
    "date": "2026-04-26",
    "title": "전세 품귀에 매매값 상승, 대출규제로 '부모찬스' 필수"
  },
  {
    "date": "2026-04-25",
    "title": "전세 급감, 월세 급증…서울 주거시장 대변동"
  },
  {
    "date": "2026-04-24",
    "title": "서울 아파트값 다시 오르고, 전세는 품귀 심화"
  },
  {
    "date": "2026-04-23",
    "title": "소형 아파트 쏠림, 전세 품귀…규제의 역설"
  },
  {
    "date": "2026-04-22",
    "title": "대출규제 역풍, 소형 아파트·전세난 동시 악화"
  },
  {
    "date": "2026-04-21",
    "title": "대출규제에 소형 아파트 몰려, 전세난 확산 중"
  },
  {
    "date": "2026-04-20",
    "title": "소형 아파트 품귀, 대출규제가 부른 '이상 현상'"
  },
  {
    "date": "2026-04-19",
    "title": "대출 규제에 소형 아파트 몰려, 전세난 확산 중"
  },
  {
    "date": "2026-04-18",
    "title": "소형 아파트 품귀, 전세난 확산 중"
  },
  {
    "date": "2026-04-17",
    "title": "소형 아파트 강세, 전세난 확산 가속화"
  }
]